transformermath/__init__.py
transformermath/attention_analyzer.py
transformermath/data_creator.py
transformermath/encoded_representations.py
transformermath/evaluator.py
transformermath/general_helper.py
transformermath/main.py
transformermath/minGPT.py
transformermath/prober.py
transformermath/run_config.py
transformermath/run_device.py
transformermath/tokenizer.py
transformermath/trainer.py
transformermath/visualiser.py
transformermath-0.1.13.dist-info/METADATA
transformermath-0.1.13.dist-info/WHEEL
transformermath-0.1.13.dist-info/top_level.txt
transformermath-0.1.13.dist-info/RECORD
