Metadata-Version: 2.1
Name: transformermath
Version: 0.1.13
Requires-Dist: matplotlib ==3.4.3
Requires-Dist: numpy >=1.22
Requires-Dist: pandas ==1.3.5
Requires-Dist: scikit-learn ==1.0.2
Requires-Dist: plotly ==5.6.0
Requires-Dist: umap-learn >=0.5.3
Requires-Dist: torch >=1.10.2
Requires-Dist: seaborn ==0.11.2
Requires-Dist: scipy ==1.7.3
